[
    {
        "product_id": 1,
        "category": "All products",
        "slug": "all-products"
    },
    {
        "product_id": 2,
        "category": "Laptop",
        "slug": "Laptop"
    },
   
    
    {
        "product_id": 3,
        "category": "Phone",
        "slug": "Phone"
    },
    
   
    {
        "product_id": 4,
        "category": "Accessory",
        "slug": "Accessory"
    },
    {
        "product_id": 5,
        "category": "Watch",
        "slug": "Watch"
    }
  
]